{
  "SaveName": "",
  "GameMode": "",
  "Gravity": 0.5,
  "PlayArea": 0.5,
  "Date": "",
  "Table": "",
  "Sky": "",
  "Note": "",
  "Rules": "",
  "XmlUI": "",
  "LuaScript": "",
  "LuaScriptState": "",
  "ObjectStates": [
    {
      "Name": "Deck",
      "Transform": {
        "posX": -0.317324,
        "posY": 1.02974081,
        "posZ": -4.80218267,
        "rotX": 4.616539E-05,
        "rotY": 180.014542,
        "rotZ": -2.53149956E-05,
        "scaleX": 1.0,
        "scaleY": 1.0,
        "scaleZ": 1.0
      },
      "Nickname": "",
      "Description": "",
      "GMNotes": "",
      "ColorDiffuse": {
        "r": 0.713235259,
        "g": 0.713235259,
        "b": 0.713235259
      },
      "Locked": false,
      "Grid": true,
      "Snap": true,
      "IgnoreFoW": false,
      "Autoraise": true,
      "Sticky": true,
      "Tooltip": true,
      "GridProjection": false,
      "HideWhenFaceDown": true,
      "Hands": false,
      "SidewaysCard": false,
      "DeckIDs": [
        100,
        100,
        100,
        100
      ],
      "CustomDeck": {
        "1": {
          "FaceURL": "https://www.frogtown.me/Images/19316cbb-d1af-4ab7-b588-78637503e986.jpg",
          "BackURL": "https://www.frogtown.me/images/gatherer/CardBack.jpg",
          "NumWidth": 1,
          "NumHeight": 1,
          "BackIsHidden": true,
          "UniqueBack": false
        }
      },
      "XmlUI": "",
      "LuaScript": "",
      "LuaScriptState": "",
      "ContainedObjects": [
        {
          "Name": "Card",
          "Transform": {
            "posX": -0.317322373,
            "posY": 1.03170049,
            "posZ": -4.80217743,
            "rotX": 4.32555862E-05,
            "rotY": 180.014587,
            "rotZ": 0.000187037964,
            "scaleX": 1.0,
            "scaleY": 1.0,
            "scaleZ": 1.0
          },
          "Nickname": "Sai, Master Thopterist",
          "Description": "",
          "GMNotes": "",
          "ColorDiffuse": {
            "r": 0.713235259,
            "g": 0.713235259,
            "b": 0.713235259
          },
          "Locked": false,
          "Grid": true,
          "Snap": true,
          "IgnoreFoW": false,
          "Autoraise": true,
          "Sticky": true,
          "Tooltip": true,
          "GridProjection": false,
          "HideWhenFaceDown": true,
          "Hands": true,
          "CardID": 100,
          "SidewaysCard": false,
          "CustomDeck": {
            "1": {
              "FaceURL": "https://www.frogtown.me/Images/19316cbb-d1af-4ab7-b588-78637503e986.jpg",
              "BackURL": "https://www.frogtown.me/images/gatherer/CardBack.jpg",
              "NumWidth": 1,
              "NumHeight": 1,
              "BackIsHidden": true,
              "UniqueBack": false
            }
          },
          "XmlUI": "",
          "LuaScript": "",
          "LuaScriptState": "",
          "GUID": "0b6d08"
        },
        {
          "Name": "Card",
          "Transform": {
            "posX": 0.09905595,
            "posY": 1.20043755,
            "posZ": -4.84802628,
            "rotX": 0.00231225952,
            "rotY": 180.0146,
            "rotZ": 0.005135493,
            "scaleX": 1.0,
            "scaleY": 1.0,
            "scaleZ": 1.0
          },
          "Nickname": "Sai, Master Thopterist",
          "Description": "",
          "GMNotes": "",
          "ColorDiffuse": {
            "r": 0.713235259,
            "g": 0.713235259,
            "b": 0.713235259
          },
          "Locked": false,
          "Grid": true,
          "Snap": true,
          "IgnoreFoW": false,
          "Autoraise": true,
          "Sticky": true,
          "Tooltip": true,
          "GridProjection": false,
          "HideWhenFaceDown": true,
          "Hands": true,
          "CardID": 100,
          "SidewaysCard": false,
          "CustomDeck": {
            "1": {
              "FaceURL": "https://www.frogtown.me/Images/19316cbb-d1af-4ab7-b588-78637503e986.jpg",
              "BackURL": "https://www.frogtown.me/images/gatherer/CardBack.jpg",
              "NumWidth": 1,
              "NumHeight": 1,
              "BackIsHidden": true,
              "UniqueBack": false
            }
          },
          "XmlUI": "",
          "LuaScript": "",
          "LuaScriptState": "",
          "GUID": "575751"
        },
        {
          "Name": "Card",
          "Transform": {
            "posX": 0.0990560055,
            "posY": 1.21429551,
            "posZ": -4.84802628,
            "rotX": 0.00153410889,
            "rotY": 180.0146,
            "rotZ": 0.00298399781,
            "scaleX": 1.0,
            "scaleY": 1.0,
            "scaleZ": 1.0
          },
          "Nickname": "Sai, Master Thopterist",
          "Description": "",
          "GMNotes": "",
          "ColorDiffuse": {
            "r": 0.713235259,
            "g": 0.713235259,
            "b": 0.713235259
          },
          "Locked": false,
          "Grid": true,
          "Snap": true,
          "IgnoreFoW": false,
          "Autoraise": true,
          "Sticky": true,
          "Tooltip": true,
          "GridProjection": false,
          "HideWhenFaceDown": true,
          "Hands": true,
          "CardID": 100,
          "SidewaysCard": false,
          "CustomDeck": {
            "1": {
              "FaceURL": "https://www.frogtown.me/Images/19316cbb-d1af-4ab7-b588-78637503e986.jpg",
              "BackURL": "https://www.frogtown.me/images/gatherer/CardBack.jpg",
              "NumWidth": 1,
              "NumHeight": 1,
              "BackIsHidden": true,
              "UniqueBack": false
            }
          },
          "XmlUI": "",
          "LuaScript": "",
          "LuaScriptState": "",
          "GUID": "0b6d08"
        },
        {
          "Name": "Card",
          "Transform": {
            "posX": -0.3846099,
            "posY": 1.20340562,
            "posZ": -4.815056,
            "rotX": -0.000289333373,
            "rotY": 180.0146,
            "rotZ": 0.000385259249,
            "scaleX": 1.0,
            "scaleY": 1.0,
            "scaleZ": 1.0
          },
          "Nickname": "Sai, Master Thopterist",
          "Description": "",
          "GMNotes": "",
          "ColorDiffuse": {
            "r": 0.713235259,
            "g": 0.713235259,
            "b": 0.713235259
          },
          "Locked": false,
          "Grid": true,
          "Snap": true,
          "IgnoreFoW": false,
          "Autoraise": true,
          "Sticky": true,
          "Tooltip": true,
          "GridProjection": false,
          "HideWhenFaceDown": true,
          "Hands": true,
          "CardID": 100,
          "SidewaysCard": false,
          "CustomDeck": {
            "1": {
              "FaceURL": "https://www.frogtown.me/Images/19316cbb-d1af-4ab7-b588-78637503e986.jpg",
              "BackURL": "https://www.frogtown.me/images/gatherer/CardBack.jpg",
              "NumWidth": 1,
              "NumHeight": 1,
              "BackIsHidden": true,
              "UniqueBack": false
            }
          },
          "XmlUI": "",
          "LuaScript": "",
          "LuaScriptState": "",
          "GUID": "0b6d08"
        }
      ],
      "GUID": "318f84"
    }
  ],
  "TabStates": {},
  "VersionNumber": ""
}